mips_verilog/rtl/alu_fwd.v
// =============================================================
// ALU — matches your C++ switch(ALUOp) in execute()
// =============================================================
module alu (
    input  wire [31:0] a,
    input  wire [31:0] b,
    input  wire [5:0]  op,
    output reg  [31:0] result,
    output wire        zero      // a == b (used by BEQ)
);
    always @(*) begin
        case (op)
            6'h20: result = a + b;                                    // ADD
            6'h22: result = a - b;                                    // SUB
            6'h24: result = a & b;                                    // AND
            6'h25: result = a | b;                                    // OR
            6'h2A: result = ($signed(a) < $signed(b)) ? 32'd1 : 32'd0; // SLT
            default: result = 32'd0;
        endcase
    end
    // BEQ checks equality of the two ORIGINAL operands, not the SUB result
    assign zero = (a == b);
endmodule

// =============================================================
// Forwarding Unit — mirrors your forward() lambda in execute()
// Priority: EX/MEM > MEM/WB
// fwd: 2'b00 = register file,  2'b10 = EX/MEM,  2'b01 = MEM/WB
// =============================================================
module forwarding_unit (
    input  wire [4:0] IDEX_rs,
    input  wire [4:0] IDEX_rt,
    input  wire [4:0] EXMEM_rd,
    input  wire       EXMEM_RegWrite,
    input  wire [4:0] MEMWB_rd,
    input  wire       MEMWB_RegWrite,
    output reg  [1:0] fwd_a,
    output reg  [1:0] fwd_b
);
    always @(*) begin
        // --- Forward A (rs) ---
        if (EXMEM_RegWrite && EXMEM_rd != 0 && EXMEM_rd == IDEX_rs)
            fwd_a = 2'b10;
        else if (MEMWB_RegWrite && MEMWB_rd != 0 && MEMWB_rd == IDEX_rs)
            fwd_a = 2'b01;
        else
            fwd_a = 2'b00;

        // --- Forward B (rt) ---
        if (EXMEM_RegWrite && EXMEM_rd != 0 && EXMEM_rd == IDEX_rt)
            fwd_b = 2'b10;
        else if (MEMWB_RegWrite && MEMWB_rd != 0 && MEMWB_rd == IDEX_rt)
            fwd_b = 2'b01;
        else
            fwd_b = 2'b00;
    end
endmodule

mips_verilog/rtl/control_unit.v
// =============================================================
// Control Unit — decodes opcode into pipeline control signals
// Matches the switch/case in your C++ decode() stage exactly
// =============================================================
module control_unit (
    input  wire [5:0] opcode,
    input  wire [5:0] funct,        // used for R-type ALUOp
    output reg        RegDst,
    output reg        ALUSrc,
    output reg        MemtoReg,
    output reg        RegWrite,
    output reg        MemRead,
    output reg        MemWrite,
    output reg        Branch,
    output reg [5:0]  ALUOp         // funct field for R-type, fixed code otherwise
);
    always @(*) begin
        // Safe defaults — bubble / unknown opcode
        {RegDst, ALUSrc, MemtoReg, RegWrite,
         MemRead, MemWrite, Branch} = 7'b0;
        ALUOp = 6'h00;

        case (opcode)
            6'h00: begin // R-type: add, sub, and, or, slt
                RegDst   = 1; RegWrite = 1;
                ALUOp    = funct;       // pass funct directly to ALU
            end
            6'h08: begin // addi
                ALUSrc   = 1; RegWrite = 1;
                ALUOp    = 6'h20;       // ADD
            end
            6'h23: begin // lw
                ALUSrc   = 1; MemtoReg = 1;
                RegWrite = 1; MemRead  = 1;
                ALUOp    = 6'h20;
            end
            6'h2B: begin // sw
                ALUSrc   = 1; MemWrite = 1;
                ALUOp    = 6'h20;
            end
            6'h04: begin // beq
                Branch   = 1;
                ALUOp    = 6'h22;       // SUB (check zero)
            end
        endcase
    end
endmodule

mips_verilog/rtl/mips_pipeline.v
// =============================================================
// 5-Stage Pipelined MIPS CPU
// Direct RTL translation of your C++ MIPSSimulator class.
//
// Mapping to C++ methods:
//   fetch()          → IF stage
//   decode()         → ID stage
//   execute()        → EX stage  (includes forwarding unit)
//   memory_access()  → MEM stage
//   write_back()     → WB stage
//
// Latch naming mirrors your structs:
//   IF_ID_Latch  → ifid_*
//   ID_EX_Latch  → idex_*
//   EX_MEM_Latch → exmem_*
//   MEM_WB_Latch → memwb_*
// =============================================================
`timescale 1ns/1ps

module mips_pipeline (
    input wire clk,
    input wire rst_n
);

// ---------------------------------------------------------------
// Instruction Memory (ROM)
// ---------------------------------------------------------------
reg [31:0] imem [0:255];
initial $readmemh("scripts/program.hex", imem, 0, 5); // 6 instructions

// ---------------------------------------------------------------
// Data Memory (matches your DataMemory[1024])
// ---------------------------------------------------------------
reg [31:0] dmem [0:255];   // 256 words = 1KB (word-addressed)

// ---------------------------------------------------------------
// Register File (32 × 32-bit)
// ---------------------------------------------------------------
reg [31:0] regfile [0:31];
integer i;
initial for (i = 0; i < 32; i = i + 1) regfile[i] = 32'd0;

// ==============================================================
// IF — Instruction Fetch
// ==============================================================
reg [31:0] PC;

// IF/ID pipeline register (= IF_ID_Latch in C++)
reg [31:0] ifid_PC4;
reg [31:0] ifid_instr;
reg        ifid_valid;

wire [31:0] IF_instr = imem[PC[9:2]];   // word-addressed fetch

// ==============================================================
// ID — Instruction Decode / Register Read
// ==============================================================
wire [5:0]  ID_opcode = ifid_instr[31:26];
wire [4:0]  ID_rs     = ifid_instr[25:21];
wire [4:0]  ID_rt     = ifid_instr[20:16];
wire [4:0]  ID_rd     = ifid_instr[15:11];
wire [5:0]  ID_funct  = ifid_instr[5:0];
wire [31:0] ID_simm   = {{16{ifid_instr[15]}}, ifid_instr[15:0]}; // sign-extend

// Control signals from control unit
wire        ID_RegDst, ID_ALUSrc, ID_MemtoReg, ID_RegWrite;
wire        ID_MemRead, ID_MemWrite, ID_Branch;
wire [5:0]  ID_ALUOp;

control_unit cu (
    .opcode   (ID_opcode),
    .funct    (ID_funct),
    .RegDst   (ID_RegDst),   .ALUSrc  (ID_ALUSrc),
    .MemtoReg (ID_MemtoReg), .RegWrite(ID_RegWrite),
    .MemRead  (ID_MemRead),  .MemWrite(ID_MemWrite),
    .Branch   (ID_Branch),   .ALUOp   (ID_ALUOp)
);

// Register file reads (with WB write-first forwarding)
// Mirrors your fix: if WB is writing the same reg, use WB data
wire [31:0] WB_data;   // declared below; Verilog allows forward reference in wire
wire [31:0] ID_rdata1 = (memwb_RegWrite && memwb_rd != 0 && memwb_rd == ID_rs)
                        ? WB_data : regfile[ID_rs];
wire [31:0] ID_rdata2 = (memwb_RegWrite && memwb_rd != 0 && memwb_rd == ID_rt)
                        ? WB_data : regfile[ID_rt];

// ID/EX pipeline register (= ID_EX_Latch in C++)
reg [31:0] idex_PC4;
reg [31:0] idex_rdata1, idex_rdata2;
reg [31:0] idex_simm;
reg [4:0]  idex_rs, idex_rt, idex_rd;
reg        idex_RegDst,  idex_ALUSrc,  idex_MemtoReg, idex_RegWrite;
reg        idex_MemRead, idex_MemWrite, idex_Branch;
reg [5:0]  idex_ALUOp;
reg        idex_valid;

// ==============================================================
// EX — Execute
// ==============================================================

// --- Forwarding unit ---
wire [1:0] fwd_a, fwd_b;

// EX/MEM and MEM/WB outputs (needed combinationally for forwarding)
// Declared as regs below; Verilog allows combinational reads before assignment
reg [4:0]  exmem_rd;
reg        exmem_RegWrite;
reg [4:0]  memwb_rd;
reg        memwb_RegWrite;
reg [31:0] exmem_alu_result;
reg [31:0] memwb_alu_result, memwb_read_data;
reg        memwb_MemtoReg;

forwarding_unit fwd_unit (
    .IDEX_rs        (idex_rs),
    .IDEX_rt        (idex_rt),
    .EXMEM_rd       (exmem_rd),
    .EXMEM_RegWrite (exmem_RegWrite),
    .MEMWB_rd       (memwb_rd),
    .MEMWB_RegWrite (memwb_RegWrite),
    .fwd_a          (fwd_a),
    .fwd_b          (fwd_b)
);

// WB data mux (used in both forwarding and write-back)
assign WB_data = memwb_MemtoReg ? memwb_read_data : memwb_alu_result;

// Forwarded operands
wire [31:0] EX_op1 = (fwd_a == 2'b10) ? exmem_alu_result :
                     (fwd_a == 2'b01) ? WB_data          : idex_rdata1;

wire [31:0] EX_op2_reg = (fwd_b == 2'b10) ? exmem_alu_result :
                         (fwd_b == 2'b01) ? WB_data          : idex_rdata2;

// ALUSrc mux — use immediate for LW/SW/ADDI, register for R-type/BEQ
wire [31:0] EX_alu_b = idex_ALUSrc ? idex_simm : EX_op2_reg;

// SW write_data: always the forwarded rt value (before ALUSrc mux)
wire [31:0] EX_st_wdata = EX_op2_reg;

// ALU
wire [31:0] EX_alu_result;
wire        EX_zero;

alu alu_inst (
    .a      (EX_op1),
    .b      (EX_alu_b),
    .op     (idex_ALUOp),
    .result (EX_alu_result),
    .zero   (EX_zero)
);

// BEQ: zero is op1 == op2 (the original register values, not alu_b)
wire EX_branch_taken = idex_Branch & (EX_op1 == EX_op2_reg);
wire [31:0] EX_branch_target = idex_PC4 + {idex_simm[29:0], 2'b00};

// Destination register mux (RegDst)
wire [4:0] EX_dest = idex_RegDst ? idex_rd : idex_rt;

// EX/MEM pipeline register (= EX_MEM_Latch in C++)
// (declared as regs above, assigned in always block below)
reg [31:0] exmem_write_data;
reg        exmem_MemtoReg, exmem_MemRead, exmem_MemWrite, exmem_Branch;
reg        exmem_valid;

// ==============================================================
// MEM — Memory Access
// ==============================================================
wire [31:0] MEM_read_data = exmem_MemRead ? dmem[exmem_alu_result[9:2]] : 32'd0;

// MEM/WB pipeline register (= MEM_WB_Latch in C++)
// (declared as regs above, assigned in always block below)
reg        memwb_RegWrite_r;   // alias — memwb_RegWrite already declared
reg        memwb_valid;

// ==============================================================
// WB — Write Back  (combinational; register file write in always)
// ==============================================================
// WB_data defined above (wire)

// ==============================================================
// Pipeline register updates + hazard logic
// ==============================================================
// flush: squash IF/ID and ID/EX when branch is taken (from EX stage)
wire flush = exmem_Branch && EX_zero;   // Note: checked before exmem latch latches

always @(posedge clk or negedge rst_n) begin
    if (!rst_n) begin
        PC           <= 32'd0;
        ifid_valid   <= 0;   ifid_instr  <= 0;   ifid_PC4 <= 0;
        idex_valid   <= 0;
        exmem_valid  <= 0;
        memwb_valid  <= 0;
        exmem_RegWrite <= 0;
        memwb_RegWrite <= 0;
    end else begin

        // ===== WB: register file write =====
        if (memwb_valid && memwb_RegWrite && memwb_rd != 0)
            regfile[memwb_rd] <= WB_data;
        regfile[0] <= 32'd0;    // $zero always 0

        // ===== MEM/WB latch =====
        memwb_valid      <= exmem_valid;
        memwb_alu_result <= exmem_alu_result;
        memwb_read_data  <= MEM_read_data;
        memwb_rd         <= exmem_rd;
        memwb_RegWrite   <= exmem_valid ? exmem_RegWrite   : 1'b0;
        memwb_MemtoReg   <= exmem_MemtoReg;

        // Data memory write (SW)
        if (exmem_valid && exmem_MemWrite)
            dmem[exmem_alu_result[9:2]] <= exmem_write_data;

        // ===== EX/MEM latch =====
        if (idex_valid) begin
            exmem_valid      <= 1;
            exmem_alu_result <= EX_alu_result;
            exmem_write_data <= EX_st_wdata;
            exmem_rd         <= EX_dest;
            exmem_RegWrite   <= idex_RegWrite;
            exmem_MemtoReg   <= idex_MemtoReg;
            exmem_MemRead    <= idex_MemRead;
            exmem_MemWrite   <= idex_MemWrite;
            exmem_Branch     <= idex_Branch;
        end else begin
            exmem_valid    <= 0;
            exmem_RegWrite <= 0;
            exmem_MemWrite <= 0;
            exmem_MemRead  <= 0;
            exmem_Branch   <= 0;
        end

        // ===== Branch: redirect PC + flush IF/ID and ID/EX =====
        if (EX_branch_taken) begin
            PC         <= EX_branch_target;
            ifid_valid <= 0;  ifid_instr <= 0;
            idex_valid <= 0;
        end else begin
            // ===== IF/ID latch =====
            if (PC[9:2] < 256) begin
                ifid_instr <= IF_instr;
                ifid_PC4   <= PC + 4;
                ifid_valid <= 1;
                PC         <= PC + 4;
            end else begin
                ifid_instr <= 0;
                ifid_valid <= 0;
            end

            // ===== ID/EX latch =====
            if (ifid_valid && ifid_instr != 0) begin
                idex_valid   <= 1;
                idex_PC4     <= ifid_PC4;
                idex_rdata1  <= ID_rdata1;
                idex_rdata2  <= ID_rdata2;
                idex_simm    <= ID_simm;
                idex_rs      <= ID_rs;
                idex_rt      <= ID_rt;
                idex_rd      <= ID_rd;
                idex_RegDst  <= ID_RegDst;
                idex_ALUSrc  <= ID_ALUSrc;
                idex_MemtoReg<= ID_MemtoReg;
                idex_RegWrite<= ID_RegWrite;
                idex_MemRead <= ID_MemRead;
                idex_MemWrite<= ID_MemWrite;
                idex_Branch  <= ID_Branch;
                idex_ALUOp   <= ID_ALUOp;
            end else begin
                idex_valid    <= 0;
                idex_RegWrite <= 0;
                idex_MemRead  <= 0;
                idex_MemWrite <= 0;
                idex_Branch   <= 0;
            end
        end

    end
end

endmodule

mips_verilog/tb/tb_mips.v
// =============================================================
// Testbench — verifies the same 5 assertions as your C++ sim:
//   R8  ($t0) = 10
//   R9  ($t1) = 5
//   R10 ($t2) = 15
//   R11 ($t3) = 15   (loaded via SW then LW)
//   DataMem[16] = 15 (SW wrote correctly)
// =============================================================
`timescale 1ns/1ps

module tb_mips;

reg clk, rst_n;
integer cycle, pass_count, fail_count;

mips_pipeline dut (
    .clk   (clk),
    .rst_n (rst_n)
);

// 10 ns clock
initial clk = 0;
always #5 clk = ~clk;

// -------------------------------------------------------
// Task: check register value
// -------------------------------------------------------
task check_reg;
    input [4:0]  reg_num;
    input [31:0] expected;
    input [79:0] name_str;   // up to 10 ASCII chars packed
    begin
        if (dut.regfile[reg_num] === expected) begin
            $display("  PASS  %s (R%0d) = %0d", name_str, reg_num, expected);
            pass_count = pass_count + 1;
        end else begin
            $display("  FAIL  %s (R%0d): got %0d, expected %0d",
                     name_str, reg_num, dut.regfile[reg_num], expected);
            fail_count = fail_count + 1;
        end
    end
endtask

// -------------------------------------------------------
// Task: check data memory (byte address)
// -------------------------------------------------------
task check_mem;
    input [31:0] byte_addr;
    input [31:0] expected;
    begin
        if (dut.dmem[byte_addr/4] === expected) begin
            $display("  PASS  DataMem[%0d] = %0d", byte_addr, expected);
            pass_count = pass_count + 1;
        end else begin
            $display("  FAIL  DataMem[%0d]: got %0d, expected %0d",
                     byte_addr, dut.dmem[byte_addr/4], expected);
            fail_count = fail_count + 1;
        end
    end
endtask

// -------------------------------------------------------
// Stimulus
// -------------------------------------------------------
initial begin
    $dumpfile("mips_pipeline.vcd");
    $dumpvars(0, tb_mips);

    pass_count = 0;
    fail_count = 0;
    cycle      = 0;

    // Reset for 2 cycles
    rst_n = 0;
    repeat(2) @(posedge clk);
    rst_n = 1;

    // Run 20 cycles — enough for 6 instructions + pipeline drain
    repeat(20) @(posedge clk);

    // -----------------------------------------------
    // Self-check — same 5 assertions as C++ sim
    // -----------------------------------------------
    $display("\n=== Verilog Pipeline Self-Check ===");
    check_reg(8,  32'd10, "$t0");
    check_reg(9,  32'd5,  "$t1");
    check_reg(10, 32'd15, "$t2");
    check_reg(11, 32'd15, "$t3");
    check_mem(32'd16, 32'd15);

    $display("\n-----------------------------------");
    $display("  Cycles run  : %0d", cycle);
    $display("  Passed      : %0d", pass_count);
    $display("  Failed      : %0d", fail_count);
    if (fail_count == 0)
        $display("  ALL TESTS PASSED");
    else
        $display("  SOME TESTS FAILED — open mips_pipeline.vcd in GTKWave");
    $display("===================================\n");

    $finish;
end

// Cycle counter
always @(posedge clk) if (rst_n) cycle = cycle + 1;

// Timeout guard
initial begin
    #5000;
    $display("TIMEOUT");
    $finish;
end

endmodule

mips_verilog/mips_pipeline.vcd
$date
	Mon Jun  1 15:33:34 2026
$end
$version
	Icarus Verilog
$end
$timescale
	1ps
$end
$scope module tb_mips $end
$var reg 1 ! clk $end
$var reg 1 " rst_n $end
$var integer 32 # cycle [31:0] $end
$var integer 32 $ fail_count [31:0] $end
$var integer 32 % pass_count [31:0] $end
$scope module dut $end
$var wire 1 & EX_branch_taken $end
$var wire 32 ' EX_st_wdata [31:0] $end
$var wire 32 ( IF_instr [31:0] $end
$var wire 1 ! clk $end
$var wire 1 ) flush $end
$var wire 1 " rst_n $end
$var wire 2 * fwd_b [1:0] $end
$var wire 2 + fwd_a [1:0] $end
$var wire 32 , WB_data [31:0] $end
$var wire 32 - MEM_read_data [31:0] $end
$var wire 32 . ID_simm [31:0] $end
$var wire 5 / ID_rt [4:0] $end
$var wire 5 0 ID_rs [4:0] $end
$var wire 32 1 ID_rdata2 [31:0] $end
$var wire 32 2 ID_rdata1 [31:0] $end
$var wire 5 3 ID_rd [4:0] $end
$var wire 6 4 ID_opcode [5:0] $end
$var wire 6 5 ID_funct [5:0] $end
$var wire 1 6 ID_RegWrite $end
$var wire 1 7 ID_RegDst $end
$var wire 1 8 ID_MemtoReg $end
$var wire 1 9 ID_MemWrite $end
$var wire 1 : ID_MemRead $end
$var wire 1 ; ID_Branch $end
$var wire 1 < ID_ALUSrc $end
$var wire 6 = ID_ALUOp [5:0] $end
$var wire 1 > EX_zero $end
$var wire 32 ? EX_op2_reg [31:0] $end
$var wire 32 @ EX_op1 [31:0] $end
$var wire 5 A EX_dest [4:0] $end
$var wire 32 B EX_branch_target [31:0] $end
$var wire 32 C EX_alu_result [31:0] $end
$var wire 32 D EX_alu_b [31:0] $end
$var reg 32 E PC [31:0] $end
$var reg 1 F exmem_Branch $end
$var reg 1 G exmem_MemRead $end
$var reg 1 H exmem_MemWrite $end
$var reg 1 I exmem_MemtoReg $end
$var reg 1 J exmem_RegWrite $end
$var reg 32 K exmem_alu_result [31:0] $end
$var reg 5 L exmem_rd [4:0] $end
$var reg 1 M exmem_valid $end
$var reg 32 N exmem_write_data [31:0] $end
$var reg 6 O idex_ALUOp [5:0] $end
$var reg 1 P idex_ALUSrc $end
$var reg 1 Q idex_Branch $end
$var reg 1 R idex_MemRead $end
$var reg 1 S idex_MemWrite $end
$var reg 1 T idex_MemtoReg $end
$var reg 32 U idex_PC4 [31:0] $end
$var reg 1 V idex_RegDst $end
$var reg 1 W idex_RegWrite $end
$var reg 5 X idex_rd [4:0] $end
$var reg 32 Y idex_rdata1 [31:0] $end
$var reg 32 Z idex_rdata2 [31:0] $end
$var reg 5 [ idex_rs [4:0] $end
$var reg 5 \ idex_rt [4:0] $end
$var reg 32 ] idex_simm [31:0] $end
$var reg 1 ^ idex_valid $end
$var reg 32 _ ifid_PC4 [31:0] $end
$var reg 32 ` ifid_instr [31:0] $end
$var reg 1 a ifid_valid $end
$var reg 1 b memwb_MemtoReg $end
$var reg 1 c memwb_RegWrite $end
$var reg 32 d memwb_alu_result [31:0] $end
$var reg 5 e memwb_rd [4:0] $end
$var reg 32 f memwb_read_data [31:0] $end
$var reg 1 g memwb_valid $end
$var integer 32 h i [31:0] $end
$scope module alu_inst $end
$var wire 32 i a [31:0] $end
$var wire 32 j b [31:0] $end
$var wire 6 k op [5:0] $end
$var wire 1 > zero $end
$var reg 32 l result [31:0] $end
$upscope $end
$scope module cu $end
$var wire 6 m funct [5:0] $end
$var wire 6 n opcode [5:0] $end
$var reg 6 o ALUOp [5:0] $end
$var reg 1 < ALUSrc $end
$var reg 1 ; Branch $end
$var reg 1 : MemRead $end
$var reg 1 9 MemWrite $end
$var reg 1 8 MemtoReg $end
$var reg 1 7 RegDst $end
$var reg 1 6 RegWrite $end
$upscope $end
$scope module fwd_unit $end
$var wire 1 J EXMEM_RegWrite $end
$var wire 5 p EXMEM_rd [4:0] $end
$var wire 5 q IDEX_rs [4:0] $end
$var wire 5 r IDEX_rt [4:0] $end
$var wire 1 c MEMWB_RegWrite $end
$var wire 5 s MEMWB_rd [4:0] $end
$var reg 2 t fwd_a [1:0] $end
$var reg 2 u fwd_b [1:0] $end
$upscope $end
$upscope $end
$scope task check_mem $end
$var reg 32 v byte_addr [31:0] $end
$var reg 32 w expected [31:0] $end
$upscope $end
$scope task check_reg $end
$var reg 32 x expected [31:0] $end
$var reg 80 y name_str [79:0] $end
$var reg 5 z reg_num [4:0] $end
$upscope $end
$upscope $end
$enddefinitions $end
$comment Show the parameter values. $end
$dumpall
$end
#0
$dumpvars
bx z
bx y
bx x
bx w
bx v
b0 u
b0 t
bx s
bx r
bx q
bx p
b0 o
b0 n
b0 m
bx l
bx k
bx j
bx i
b100000 h
0g
bx f
bx e
bx d
0c
xb
0a
b0 `
b0 _
0^
bx ]
bx \
bx [
bx Z
bx Y
bx X
xW
xV
bx U
xT
xS
xR
xQ
xP
bx O
bx N
0M
bx L
bx K
0J
xI
xH
xG
xF
b0 E
bx D
bx C
bx B
bx A
bx @
bx ?
x>
b0 =
0<
0;
0:
09
08
17
16
b0 5
b0 4
b0 3
b0 2
b0 1
b0 0
b0 /
b0 .
bx -
bx ,
b0 +
b0 *
x)
b100000000010000000000000001010 (
bx '
x&
b0 %
b0 $
b0 #
0"
0!
$end
#5000
1!
#10000
0!
#15000
b100000 =
b100000 o
1<
07
16
0&
b100000000010010000000000000101 (
b1000 4
b1000 n
b1000 /
b1010 5
b1010 m
b1010 .
0)
b0 -
0Q
0S
0R
0W
b100 E
1a
b100 _
b100000000010000000000000001010 `
0F
0G
0H
b1 #
1"
1!
#20000
0!
#25000
b1010 C
b1010 l
b0 '
b0 ?
0>
b0 @
b0 i
b100000 =
b100000 o
1<
16
b1000 A
b1010 D
b1010 j
b101100 B
b1000010010101000000100000 (
b1001 /
b101 5
b101 m
b101 .
b100000 O
b100000 k
1W
0T
1P
0V
b0 X
b1000 \
b1000 r
b0 [
b0 q
b1010 ]
b0 Z
b0 Y
b100 U
1^
b1000 E
b1000 _
b100000000010010000000000000101 `
b0 f
b10 #
1!
#30000
0!
#35000
b101 C
b101 l
17
b100000 =
b100000 o
0<
16
b1001 A
b101 D
b101 j
b10101100000010100000000000010000 (
b0 4
b0 n
b1000 0
b1010 3
b100000 5
b100000 m
b101000000100000 .
b1001 \
b1001 r
b101 ]
b11100 B
b1000 U
b1100 E
b1100 _
b1000010010101000000100000 `
0I
1J
b1000 L
b1000 p
b0 N
b1010 K
1M
b11 #
1!
#40000
0!
#45000
b1010 @
b1010 i
b1111 C
b1111 l
19
1<
b100000 =
b100000 o
07
06
b101 '
b101 ?
b1010 A
0>
b101 D
b101 j
b10001100000010110000000000010000 (
b101011 4
b101011 n
b0 0
b1010 /
b0 3
b10000 5
b10000 m
b10000 .
b10 *
b10 u
b1 +
b1 t
b1010 ,
0P
1V
b1010 X
b1000 [
b1000 q
b101000000100000 ]
b10100000010001100 B
b1100 U
b10000 E
b10000 _
b10101100000010100000000000010000 `
b1001 L
b1001 p
b101 K
0b
1c
b1000 e
b1000 s
b1010 d
1g
b100 #
1!
#50000
0!
#55000
b0 @
b0 i
b10000 C
b10000 l
1:
16
18
b100000 =
b100000 o
1<
09
b10000 D
b10000 j
b10001010010111111111111111010 (
b100011 4
b100011 n
b1011 /
b1111 '
b1111 ?
b0 +
b0 t
b101 ,
1S
0W
1P
0V
b0 X
b1010 \
b1010 r
b0 [
b0 q
b10000 ]
b1010000 B
b10000 U
b10100 E
b10100 _
b10001100000010110000000000010000 `
b1010 L
b1010 p
b101 N
b1111 K
b1001 e
b1001 s
b101 d
b101 #
1!
#60000
0!
#65000
b1111 2
1;
b100010 =
b100010 o
0<
08
06
0:
b1011 A
bx (
b100 4
b100 n
b1010 0
b11111 3
b111010 5
b111010 m
b11111111111111111111111111111010 .
b0 '
b0 ?
b0 *
b0 u
b1111 ,
0S
1R
1W
1T
b1011 \
b1011 r
b1010100 B
b10100 U
b11000 E
b11000 _
b10001010010111111111111111010 `
1H
0J
b1111 N
b10000 K
b1010 e
b1010 s
b1111 d
b110 #
1!
#70000
0!
#75000
b1111 @
b1111 i
bx 1
b0 =
b0 o
0;
b10000 '
b10000 ?
bx 2
b11111111111111111111111111111111 C
b11111111111111111111111111111111 l
0&
0>
b10000 D
b10000 j
bx 4
bx n
bx 0
bx /
bx 3
bx 5
bx m
bx .
b1111 -
b10 *
b10 u
b10000 ,
b100010 O
b100010 k
1Q
0R
0W
0T
0P
b11111 X
b1010 [
b1010 q
b11111111111111111111111111111010 ]
b1111 Y
b0 B
b11000 U
b11100 E
b11100 _
bx `
0H
1G
1I
1J
b1011 L
b1011 p
b0 N
0c
b10000 d
b111 #
1!
#80000
0!
#85000
1)
1>
b0 C
b0 l
b1111 D
b1111 j
b0 -
b1111 '
b1111 ?
b1111 ,
b1 *
b1 u
0Q
0^
b100000 E
b100000 _
1F
0G
0I
0J
b10000 N
b11111111111111111111111111111111 K
1b
1c
b1011 e
b1011 s
b1111 f
b1000 #
1!
#90000
0!
#95000
b1111 C
b1111 l
0>
b0 D
b0 j
b0 '
b0 ?
0)
b0 *
b0 u
b11111111111111111111111111111111 ,
b100100 E
b100100 _
0F
0M
0b
0c
b0 f
b11111111111111111111111111111111 d
b1001 #
1!
#100000
0!
#105000
b101000 E
b101000 _
0g
b1010 #
1!
#110000
0!
#115000
b101100 E
b101100 _
b1011 #
1!
#120000
0!
#125000
b110000 E
b110000 _
b1100 #
1!
#130000
0!
#135000
b110100 E
b110100 _
b1101 #
1!
#140000
0!
#145000
b111000 E
b111000 _
b1110 #
1!
#150000
0!
#155000
b111100 E
b111100 _
b1111 #
1!
#160000
0!
#165000
b1000000 E
b1000000 _
b10000 #
1!
#170000
0!
#175000
b1000100 E
b1000100 _
b10001 #
1!
#180000
0!
#185000
b1001000 E
b1001000 _
b10010 #
1!
#190000
0!
#195000
b1001100 E
b1001100 _
b10011 #
1!
#200000
0!
#205000
b1010000 E
b1010000 _
b10100 #
1!
#210000
0!
#215000
b1010100 E
b1010100 _
b1111 w
b10000 v
b101 %
b10101 #
b1001000111010000110011 y
b1111 x
b1011 z
1!
